{
	"gerTitle": "Sänfte",
	"year": "1800",
	"gerHeader": "<b><size=30>Sänfte der Dresdner Hofchaisenträger</size></b> <br><br>um 1800",
	"gerPreDescr": "<b>Maße mit Trageholmen (L/B/H)</b>\n2.000/730/1.720 mm\n\n<b>Eigengewicht</b>\nca. 50 kg\n\n<b>Sitzplätze</b>\n1",
	"gerDescr": "Miet-Sänften – auch Portechaisen – waren teuer und nur für wohlhabende Bürger erschwinglich. Die Passagiere gelangten damit nicht besonders schnell zu Terminen, aber sie waren weder dem Straßenschmutz noch dem Regen ausgesetzt. \nDie Sänfte hat Glasfenster und einen gepolsterten Sitz. Für Damen mit besonders anspruchsvollen Frisuren kann das Dach angehoben und geöffnet werden. \nZwei Männer trugen die Portechaise an zwei Holmen und Tragegurten.\nRatsherr Johann Friedrich Landsberger führte die ersten öffentlichen Sänften in Dresden 1705 ein. Im gleichen Jahr veröffentlichte der Rat der Stadt Dresden eine Ordnung, die auch den Beförderungstarif enthielt. Für Angehörige des Sächsischen Hofes betrieben die Dresdner Hofchaisenträger ein zweites Unternehmen. \n1878 endete in Dresden diese Art der Beförderung. Die Sänften waren der Konkurrenz der Pferdedroschken und dem Ausbau des Straßenbahnnetzes nicht mehr gewachsen."
}